<DOMSymbolItem xmlns:xsi="http://www.w3.org/2001/XMLSchema-instance" xmlns="http://ns.adobe.com/xfl/2008/" name="Characters/Boss2-Vandheer/assets/graphics/VDL-Shape-Arm" itemID="54d47e4a-00001297" symbolType="graphic" lastModified="1423212106">
  <timeline>
    <DOMTimeline name="VDL-Shape-Arm">
      <layers>
        <DOMLayer name="Layer 1" color="#4FFF4F" current="true" isSelected="true">
          <frames>
            <DOMFrame index="0" keyMode="9728">
              <elements>
                <DOMShape>
                  <fills>
                    <FillStyle index="1">
                      <SolidColor/>
                    </FillStyle>
                    <FillStyle index="2">
                      <SolidColor color="#333333"/>
                    </FillStyle>
                  </fills>
                  <edges>
                    <Edge fillStyle1="2" edges="!37 -45|7 -77!7 -77|14 -82!14 -82[15 -82 16 -82!16 -82[43 -67 53 -38!53 -38[58 -24 61 -9!61 -9[64 6 63 22!63 22[63 35 60 49"/>
                    <Edge fillStyle0="2" fillStyle1="1" edges="!37 -45[38 -44 39 -43!39 -43[50 -32 53 -17!53 -17[55 -2 54 9!54 9[53 20 50 25!50 25[47 29 47 31!47 31|31 35!31 35[22 32 14 28!14 28[5 23 -2 16!-2 16[-10 9 -11 1!-11 1[-9 -25 -1 -34!-1 -34|-23 -68!1 -11[1 -4 4 4!4 4[8 14 21 20!21 20[31
 26 43 21!43 21[50 10 49 -4!49 -4[51 -21 41 -31!41 -31[39 -34 37 -36!37 -36[10 -39 1 -11"/>
                    <Edge fillStyle0="1" fillStyle1="2" edges="
!60 49|50 65!50 65[34 73 29 71!29 71[12 64 -2 55!-2 55[-18 45 -31 32!-31 32[-40 24 -48 16!-48 16[-49 12 -49 8!-49 8[-49 -9 -47 -25"/>
                    <Edge fillStyle1="1" edges="
!60 49[62 69 69 90!69 90[71 96 73 103!73 103[77 118 79 133!79 133[85 170 88 211!88 211[91 251 100 261!100 261[109 270 108 301!108 301[106 332 97 468!97 468|115 550!115 550[98 573 75 593!75 593[68 601 59 607!59 607[58 608 57 608!57 608
[52 607 51 606!51 606[45 591 42 575!42 575|35 570!35 570[22 559 32 540!32 540[40 523 44 506!44 506[57 446 41 385!41 385[32 353 33 322!33 322[34 304 30 286!30 286[26 271 17 258!17 258[-13 216 -18 159!-18 159[-21 130 -24 103!-24 103[-26
 93 -27 84!-27 84|-31 74!-31 74[-33 73 -34 72!-34 72[-44 56 -55 42!-55 42[-65 28 -61 15!-61 15[-55 -5 -47 -25"/>
                    <Edge fillStyle1="2" edges="
!-47 -25|-30 -74!-30 -74|-23 -68"/>
                    <Edge fillStyle1="1" edges="
!-23 -68[-19 -73 -11 -74!-11 -74[16 -64 37 -45"/>
                    <Edge cubics="!14 -82(;15,-82 15,-82 16,-82q14 -82Q15 -82q16 -82);"/>
                    <Edge cubics="!79 133(;78,123 76,113 73,103q79 133Q77 118q73 103);"/>
                    <Edge cubics="!73 103(73,103;72,98 70,94 69,90q73 103Q71 96q69 90);"/>
                    <Edge cubics="!69 90(69,90;64,76 61,62 60,49q69 90Q62 69q60 49);"/>
                    <Edge cubics="!-11 -74(;-16,-73 -20,-71 -23,-68q-11 -74Q-19 -73q-23 -68);"/>
                    <Edge cubics="!-30 -74(;-28,-72 -26,-70 -23,-68q-30 -74Q-27 -71q-23 -68);"/>
                    <Edge cubics="!-47 -25(;-52,-12 -57,2 -61,15q-47 -25Q-55 -5q-61 15);"/>
                    <Edge cubics="!-47 -25(-47,-25;-42,-42 -37,-59 -30,-74q-47 -25Q-40 -51q-30 -74);"/>
                    <Edge cubics="!-31 74(;-31,74 -27,84 -27,84q-31 74 -27 84);"/>
                    <Edge cubics="!-34 72(;-33,73 -32,73 -31,74q-34 72Q-33 73q-31 74);"/>
                    <Edge cubics="!-24 103(;-25,96 -26,90 -27,84q-24 103Q-26 93q-27 84);"/>
                    <Edge cubics="!-55 42(;-48,51 -41,61 -34,72q-55 42Q-44 56q-34 72);"/>
                    <Edge cubics="!-61 15(-61,15;-64,24 -62,33 -55,42q-61 15Q-65 28q-55 42);"/>
                    <Edge cubics="!100 261(;94,254 90,238 88,211q100 261Q91 251q88 211);"/>
                    <Edge cubics="!33 322(33,322;34,310 33,298 30,286q33 322Q34 304q30 286);"/>
                    <Edge cubics="!41 385(41,385;35,364 32,343 33,322q41 385Q32 353q33 322);"/>
                    <Edge cubics="!100 261(;106,267 109,280 108,301q100 261Q109 270q108 301);"/>
                    <Edge cubics="!30 286(;27,276 23,267 17,258q30 286Q26 271q17 258);"/>
                    <Edge cubics="!42 575(;42,575 35,570 35,570q42 575 35 570);"/>
                    <Edge cubics="!35 570(;26,563 25,553 32,540q35 570Q22 559q32 540);"/>
                    <Edge cubics="!59 607(;58,608 58,608 57,608q59 607Q58 608q57 608);"/>
                    <Edge cubics="!57 608(57,608;54,607 52,607 51,606q57 608Q52 607q51 606);"/>
                    <Edge cubics="!75 593(;70,598 65,603 59,607q75 593Q68 601q59 607);"/>
                    <Edge cubics="!51 606(;47,596 44,586 42,575q51 606Q45 591q42 575);"/>
                    <Edge cubics="!97 468(;97,468 115,550 115,550q97 468 115 550);"/>
                    <Edge cubics="!115 550(;104,565 90,580 75,593q115 550Q98 573q75 593);"/>
                    <Edge cubics="!32 540(32,540;37,529 41,517 44,506q32 540Q40 523q44 506);"/>
                    <Edge cubics="!108 301(108,301;107,322 103,377 97,468q108 301Q106 332q97 468);"/>
                    <Edge cubics="!44 506(44,506;53,466 52,426 41,385q44 506Q57 446q41 385);"/>
                    <Edge cubics="!-18 159(;-20,140 -22,121 -24,103q-18 159Q-21 130q-24 103);"/>
                    <Edge cubics="!7 -77(;8,-79 11,-81 14,-82q7 -77Q9 -80q14 -82);"/>
                    <Edge cubics="!37 -45(;23,-58 7,-67 -11,-74q37 -45Q16 -64q-11 -74);"/>
                    <Edge cubics="!88 211(;86,184 83,158 79,133q88 211Q85 170q79 133);"/>
                    <Edge cubics="!17 258(17,258;-3,230 -15,197 -18,159q17 258Q-13 216q-18 159);"/>
                    <Edge cubics="!-1 -34(;-1,-34 -23,-68 -23,-68q-1 -34 -23 -68);"/>
                    <Edge cubics="!-48 16(;-41,21 -35,27 -31,32q-48 16Q-37 24q-31 32);"/>
                    <Edge cubics="!7 -77(7,-77;7,-77 37,-45 37,-45q7 -77 37 -45);"/>
                    <Edge cubics="!39 -43(;38,-44 38,-44 37,-45q39 -43Q38 -44q37 -45);"/>
                    <Edge cubics="!16 -82(;34,-72 46,-57 53,-38q16 -82Q43 -67q53 -38);"/>
                    <Edge cubics="!61 -9(;63,1 64,11 63,22q61 -9Q64 6q63 22);"/>
                    <Edge cubics="!43 21(;48,14 50,5 49,-4q43 21Q50 10q49 -4);"/>
                    <Edge cubics="!21 20(;28,24 35,24 43,21q21 20Q31 26q43 21);"/>
                    <Edge cubics="!54 9(;55,2 54,-7 53,-17q54 9Q55 -2q53 -17);"/>
                    <Edge cubics="!50 25(;52,22 53,16 54,9q50 25Q53 20q54 9);"/>
                    <Edge cubics="!49 -4(;50,-15 48,-24 41,-31q49 -4Q51 -21q41 -31);"/>
                    <Edge cubics="!53 -38(;56,-29 59,-19 61,-9q53 -38Q58 -24q61 -9);"/>
                    <Edge cubics="!41 -31(;40,-33 38,-35 37,-36q41 -31Q39 -34q37 -36);"/>
                    <Edge cubics="!53 -17(;51,-27 46,-36 39,-43q53 -17Q50 -32q39 -43);"/>
                    <Edge cubics="!31 35(;31,35 47,31 47,31q31 35 47 31);"/>
                    <Edge cubics="!50 65(;39,70 32,72 29,71q50 65Q34 73q29 71);"/>
                    <Edge cubics="!60 49(;60,49 50,65 50,65q60 49 50 65);"/>
                    <Edge cubics="!63 22(;63,31 62,40 60,49q63 22Q63 35q60 49);"/>
                    <Edge cubics="!14 28(;19,31 25,33 31,35q14 28Q22 32q31 35);"/>
                    <Edge cubics="!47 31(;47,30 48,28 50,25q47 31Q47 29q50 25);"/>
                    <Edge cubics="!-48 16(;-49,13 -49,11 -49,8q-48 16Q-49 12q-49 8);"/>
                    <Edge cubics="!-49 8(;-49,-3 -48,-14 -47,-25q-49 8Q-49 -9q-47 -25);"/>
                    <Edge cubics="!-11 1(;-10,6 -7,11 -2,16q-11 1Q-10 9q-2 16);"/>
                    <Edge cubics="!1 -11(;1,-6 2,-1 4,4q1 -11Q1 -4q4 4);"/>
                    <Edge cubics="!-1 -34(;-6,-28 -10,-16 -11,1q-1 -34Q-9 -25q-11 1);"/>
                    <Edge cubics="!-2 55(;-13,48 -22,41 -31,32q-2 55Q-18 45q-31 32);"/>
                    <Edge cubics="!29 71(;18,66 7,61 -2,55q29 71Q12 64q-2 55);"/>
                    <Edge cubics="!4 4(;7,11 12,16 21,20q4 4Q8 14q21 20);"/>
                    <Edge cubics="!37 -36(;19,-38 7,-30 1,-11q37 -36Q10 -39q1 -11);"/>
                    <Edge cubics="!-2 16(;3,21 8,25 14,28q-2 16Q5 23q14 28);"/>
                  </edges>
                </DOMShape>
              </elements>
            </DOMFrame>
          </frames>
        </DOMLayer>
      </layers>
    </DOMTimeline>
  </timeline>
</DOMSymbolItem>