<DOMSymbolItem xmlns:xsi="http://www.w3.org/2001/XMLSchema-instance" xmlns="http://ns.adobe.com/xfl/2008/" name="Characters/_Natube/assets/shape/Natude-shape-06" itemID="556ac67b-000007db" symbolType="graphic" lastModified="1433060987">
  <timeline>
    <DOMTimeline name="Natude-shape-06">
      <layers>
        <DOMLayer name="Layer 1" color="#4F80FF" current="true" isSelected="true">
          <frames>
            <DOMFrame index="0" keyMode="9728">
              <elements>
                <DOMGroup selected="true">
                  <members>
                    <DOMShape selected="true">
                      <fills>
                        <FillStyle index="1">
                          <SolidColor/>
                        </FillStyle>
                      </fills>
                      <edges>
                        <Edge fillStyle1="1" edges="!38 295S2|26 278!26 278|14 270!14 270[-37 189 -121 135!-121 135[-139 -32 -165 -196!-165 -196[-173 -243 -178 -291!-178 -291[-182 -332 -182 -373!-182 -373[-181 -422 -170 -469!-170 -469[-170 -471 -167 -471!-167 -471[-109 -313 -78 -149!-78
 -149[-75 -133 -70 -117!-70 -117[-52 -56 -11 -1!-11 -1[80 120 137 260!137 260[144 277 150 296!150 296[173 364 181 435!181 435[182 446 179 459!179 459[177 465 169 470!169 470[130 476 112 425!112 425[94 377 64 334!64 334[51 314 38 295"/>
                      </edges>
                    </DOMShape>
                  </members>
                </DOMGroup>
              </elements>
            </DOMFrame>
          </frames>
        </DOMLayer>
      </layers>
    </DOMTimeline>
  </timeline>
</DOMSymbolItem>