<DOMSymbolItem xmlns:xsi="http://www.w3.org/2001/XMLSchema-instance" xmlns="http://ns.adobe.com/xfl/2008/" name="UI/UI-Player/assets/UI-Equipt-Label1" itemID="54e3de0b-000003b9" lastModified="1451498328">
  <timeline>
    <DOMTimeline name="UI-Equipt-Label1">
      <layers>
        <DOMLayer name="Layer 1" color="#4F80FF" current="true" isSelected="true">
          <frames>
            <DOMFrame index="0" keyMode="9728">
              <elements>
                <DOMStaticText selected="true" fontRenderingMode="standard" left="38.1" width="136.2" height="42" autoExpand="true" isSelectable="false">
                  <matrix>
                    <Matrix tx="-106.2" ty="-21"/>
                  </matrix>
                  <textRuns>
                    <DOMTextRun>
                      <characters>Boosters</characters>
                      <textAttrs>
                        <DOMTextAttrs alignment="center" aliasText="false" autoKern="false" letterSpacing="3" lineHeight="42" size="28" bitmapSize="560" face="Thinman" fillColor="#FFFFFF"/>
                      </textAttrs>
                    </DOMTextRun>
                  </textRuns>
                  <filters>
                    <DropShadowFilter blurX="4" blurY="4" color="#333333" distance="3" strength="0.4"/>
                  </filters>
                </DOMStaticText>
              </elements>
            </DOMFrame>
          </frames>
        </DOMLayer>
      </layers>
    </DOMTimeline>
  </timeline>
</DOMSymbolItem>