<DOMSymbolItem xmlns:xsi="http://www.w3.org/2001/XMLSchema-instance" xmlns="http://ns.adobe.com/xfl/2008/" name="Objects/_Swords/sword57" itemID="576d585b-00000c61" lastModified="1466783835">
  <timeline>
    <DOMTimeline name="sword57">
      <layers>
        <DOMLayer name="Layer 1" color="#4F80FF" current="true" isSelected="true">
          <frames>
            <DOMFrame index="0" keyMode="9728">
              <elements>
                <DOMShape>
                  <fills>
                    <FillStyle index="1">
                      <SolidColor/>
                    </FillStyle>
                  </fills>
                  <edges>
                    <Edge fillStyle1="1" edges="!-458 195S2[-511 200 -556 255!-556 255[-486 27 -369 16!-369 16[-272 9 -183 148!-183 148[-146 27 -2 -1460!-2 -1460[150 27 187 151!187 151[275 13 368 23!368 23[485 32 557 260!557 260[513 204 457 200!457 200[361 190 268 362!268 362[361 549
 457 542!457 542[513 535 557 474!557 474[485 721 368 733!368 733[271 742 180 584!180 584[161 639 147 700!147 700[205 865 299 875!299 875[313 875 324 875!324 875[259 949 189 942!189 942[150 937 117 914!117 914|61 951!61 951|38 949!38 949
|38 1324!38 1324|103 1387!103 1387|70 1419!70 1419[15 1501 -76 1419!-76 1419|-111 1387!-111 1387|-39 1324!-39 1324|-39 949!-39 949|-74 947!-74 947|-111 912!-111 912[-141 933 -179 937!-179 937[-248 944 -314 870!-314 870[-302 872 -288 870
!-288 870[-200 861 -141 709!-141 709[-158 644 -174 584!-174 584[-269 749 -369 737!-369 737[-486 726 -556 479!-556 479[-511 542 -458 546!-458 546[-358 553 -265 362!-265 362[-358 188 -458 195"/>
                    <Edge fillStyle0="1" edges="
!-81 362S1[-34 223 1 53!1 53[36 223 84 362!84 362[36 493 1 649!1 649[-34 495 -81 362"/>
                    <Edge cubics="!457 542(;494,537 528,515 557,474q457 542Q513 535q557 474);"/>
                    <Edge cubics="!557 260(;528,223 494,203 457,200q557 260Q513 204q457 200);"/>
                    <Edge cubics="!299 875(;308,875 317,875 324,875q299 875Q313 875q324 875);"/>
                    <Edge cubics="!557 474(;509,639 446,725 368,733q557 474Q485 721q368 733);"/>
                    <Edge cubics="!-265 362(;-327,246 -391,190 -458,195q-265 362Q-358 188q-458 195);"/>
                    <Edge cubics="!-458 546(;-391,551 -327,489 -265,362q-458 546Q-358 553q-265 362);"/>
                    <Edge cubics="!-314 870(;-306,871 -297,871 -288,870q-314 870Q-302 872q-288 870);"/>
                    <Edge cubics="!-288 870(;-229,864 -180,810 -141,709q-288 870Q-200 861q-141 709);"/>
                    <Edge cubics="!-179 937(;-225,942 -270,919 -314,870q-179 937Q-248 944q-314 870);"/>
                    <Edge cubics="!117 914(;117,914 61,951 61,951q117 914 61 951);"/>
                    <Edge cubics="!189 942(;163,939 139,929 117,914q189 942Q150 937q117 914);"/>
                    <Edge cubics="!-74 947(;-74,947 -111,912 -111,912q-74 947 -111 912);"/>
                    <Edge cubics="!-39 949(;-39,949 -74,947 -74,947q-39 949 -74 947);"/>
                    <Edge cubics="!61 951(;61,951 38,949 38,949q61 951 38 949);"/>
                    <Edge cubics="!-141 709(;-152,666 -163,624 -174,584q-141 709Q-158 644q-174 584);"/>
                    <Edge cubics="!180 584(;167,621 156,659 147,700q180 584Q161 639q147 700);"/>
                    <Edge cubics="!84 362(;52,449 24,545 1,649q84 362Q36 493q1 649);"/>
                    <Edge cubics="!1 649(;-22,546 -50,451 -81,362q1 649Q-34 495q-81 362);"/>
                    <Edge cubics="!-111 912(;-131,926 -154,934 -179,937q-111 912Q-141 933q-179 937);"/>
                    <Edge cubics="!-174 584(;-237,694 -302,745 -369,737q-174 584Q-269 749q-369 737);"/>
                    <Edge cubics="!103 1387(;103,1387 70,1419 70,1419q103 1387 70 1419);"/>
                    <Edge cubics="!70 1419(;33,1474 -15,1474 -76,1419q70 1419Q15 1501q-76 1419);"/>
                    <Edge cubics="!-76 1419(;-76,1419 -111,1387 -111,1387q-76 1419 -111 1387);"/>
                    <Edge cubics="!38 1324(;38,1324 103,1387 103,1387q38 1324 103 1387);"/>
                    <Edge cubics="!-111 1387(;-111,1387 -39,1324 -39,1324q-111 1387 -39 1324);"/>
                    <Edge cubics="!-458 195(;-493,198 -526,218 -556,255q-458 195Q-511 200q-556 255);"/>
                    <Edge cubics="!-556 479(;-526,521 -493,543 -458,546q-556 479Q-511 542q-458 546);"/>
                    <Edge cubics="!-369 737(;-447,730 -509,644 -556,479q-369 737Q-486 726q-556 479);"/>
                    <Edge cubics="!-39 1324(;-39,1324 -39,949 -39,949q-39 1324 -39 949);"/>
                    <Edge cubics="!38 949(;38,949 38,1324 38,1324q38 949 38 1324);"/>
                    <Edge cubics="!457 200(;393,193 330,247 268,362q457 200Q361 190q268 362);"/>
                    <Edge cubics="!368 733(;303,739 241,689 180,584q368 733Q271 742q180 584);"/>
                    <Edge cubics="!268 362(;330,487 393,547 457,542q268 362Q361 549q457 542);"/>
                    <Edge cubics="!324 875(;281,924 236,947 189,942q324 875Q259 949q189 942);"/>
                    <Edge cubics="!147 700(;186,810 236,868 299,875q147 700Q205 865q299 875);"/>
                    <Edge cubics="!187 151(;246,59 306,16 368,23q187 151Q275 13q368 23);"/>
                    <Edge cubics="!1 53(;24,166 52,269 84,362q1 53Q36 223q84 362);"/>
                    <Edge cubics="!-81 362(;-50,269 -22,166 1,53q-81 362Q-34 223q1 53);"/>
                    <Edge cubics="!-556 255(;-509,103 -447,23 -369,16q-556 255Q-486 27q-369 16);"/>
                    <Edge cubics="!-369 16(;-304,11 -242,55 -183,148q-369 16Q-272 9q-183 148);"/>
                    <Edge cubics="!-183 148(;-158,67 -98,-469 -2,-1460q-183 148Q-146 27q-2 -1460);"/>
                    <Edge cubics="!-2 -1460(;99,-469 162,68 187,151q-2 -1460Q150 27q187 151);"/>
                    <Edge cubics="!368 23(;446,29 509,108 557,260q368 23Q485 32q557 260);"/>
                  </edges>
                </DOMShape>
              </elements>
            </DOMFrame>
          </frames>
        </DOMLayer>
      </layers>
    </DOMTimeline>
  </timeline>
</DOMSymbolItem>