<DOMSymbolItem xmlns:xsi="http://www.w3.org/2001/XMLSchema-instance" xmlns="http://ns.adobe.com/xfl/2008/" name="Levels/Level-O/IceShard-Graphics/IceShard-Shape-10" itemID="56d2cd94-00000c7f" symbolType="graphic" lastModified="1490645159">
  <timeline>
    <DOMTimeline name="IceShard-Shape-10">
      <layers>
        <DOMLayer name="Layer 1" color="#4F80FF" current="true" isSelected="true">
          <frames>
            <DOMFrame index="0" keyMode="9728">
              <elements>
                <DOMGroup>
                  <members>
                    <DOMShape>
                      <fills>
                        <FillStyle index="1">
                          <LinearGradient>
                            <matrix>
                              <Matrix a="0.0399322509765625" b="-0.227294921875" c="0.043487548828125" d="0.0076446533203125" tx="6.7" ty="0.35"/>
                            </matrix>
                            <GradientEntry ratio="0"/>
                            <GradientEntry color="#FFFFFF" ratio="1"/>
                          </LinearGradient>
                        </FillStyle>
                        <FillStyle index="2">
                          <LinearGradient>
                            <matrix>
                              <Matrix a="0.0376739501953125" b="-0.214431762695313" c="0.03179931640625" d="0.005584716796875" tx="10.05" ty="26.15"/>
                            </matrix>
                            <GradientEntry color="#585858" ratio="0"/>
                            <GradientEntry color="#FFFFFF" ratio="1"/>
                          </LinearGradient>
                        </FillStyle>
                      </fills>
                      <edges>
                        <Edge fillStyle1="1" edges="!386 -1017[388 -994 423 -773!423 -773[461 -527 489 -368!489 -368[493 -347 525 -315!525 -315[562 -278 563 -276!563 -276[570 -264 576 -211!576 -211[585 -126 585 -125!585 -125[611 54 627 391!627 391[642 697 636 777!636 777[633 817 647 915
!647 915[662 1026 662 1113!662 1113[662 1220 653 1255!653 1255[645 1288 610 1334!610 1334[462 1525 308 1829!308 1829[265 1913 200 2009!200 2009[127 2119 104 2119!104 2119[-66 2119 -75 2118!-75 2118[-121 2111 -141 2062!-141 2062[-195 1829
 -352 1475!-352 1475[-390 1389 -456 1127!-456 1127[-525 856 -572 742!-572 742[-619 645 -623 628!-623 628[-647 542 -649 531!-649 531[-661 471 -661 395!-661 395[-661 324 -623 118!-623 118[-578 -120 -537 -171!-537 -171[-508 -207 -449 -206
!-449 -206[-403 -205 -403 -232!-403 -232[-459 -319 -459 -329!-459 -329[-459 -342 -386 -585!-386 -585[-378 -611 -376 -620!-376 -620[-364 -658 -274 -901!-274 -901[-203 -1094 -197 -1113!-197 -1113[-174 -1184 -154 -1217!-154 -1217[-139 -1242
 -96 -1289!-96 -1289[-37 -1352 -31 -1379!-31 -1379[-14 -1440 87 -1820!87 -1820[107 -1895 128 -1920!128 -1920[151 -1947 150 -2011!150 -2011[150 -2072 175 -2093!175 -2093[182 -2098 192 -2109!192 -2109[202 -2116 218 -2116!218 -2116[230 -2116
 234 -2115!234 -2115[236 -2114 245 -2112!245 -2112[334 -2086 337 -2083!337 -2083[332 -1945 332 -1906!332 -1906[332 -1884 347 -1655!347 -1655[361 -1425 360.5 -1365"/>
                        <Edge fillStyle0="1" fillStyle1="2" edges="
!386 -1017[381 -986 374 -956!374 -956[204 -1004 198 -1005!198 -1005|192 -1000!192 -1000[306 -841 351 -778!351 -778[428 -670 428 -566!428 -566[428 -549 454 -467!454 -467[480 -385 480 -288!480 -288[480 -250 431 -248!431 -248[376 -253 364
 -253!364 -253[343 -253 332 -223!332 -223[316 -178 310 -170!310 -170[367 -157 385 -157!385 -157[446 -157 473 -172!473 -172[490 -181 521 -207!521 -207[531 -196 535 -189!535 -189[539 -180 539 -166!539 -166[539 -156 531 -122!531 -122[522
 -89 522 -79!522 -79[522 10 556 311!556 311[590 617 591 655!591 655[591 660 592 901!592 901[593 1027 605 1104!605 1104[507 1137 502 1149!502 1149[498 1159 496 1205!496 1205[484 1237 449 1287!449 1287[419 1332 419 1336!419 1336[419 1380
 451 1380!451 1380[465 1380 472 1376!472 1376[477 1373 486 1362!486 1362[501 1375 501 1395!501 1395[344 1741 257 1742!257 1742[223 1742 196 1817!196 1817[153 1939 102 2015!102 2015[80 1982 41 1953!41 1953[7 1928 -15 1887!-15 1887[-86
 1759 -225 1177!-225 1177[-287 920 -339 847!-339 847[-361 817 -363 811!-363 811[-370 791 -370 730!-370 730[-370 679 -347 662!-347 662[-322 655 -321 655!-321 655[-313 655 -275 721!-275 721[-238 786 -238 790!-238 790[-238 868 -135 1002
!-135 1002|27 1329!27 1329[55 1386 221 1704!221 1704[246 1683 255 1632!255 1632[270 1548 284 1508!284 1508[289 1493 327 1451!327 1451[364 1407 369 1396!369 1396|372 1378!372 1378[342 1396 299 1447!299 1447[265 1486 242 1486!242 1486[208
 1486 183 1429!183 1429[177 1417 153 1341!153 1341[147 1322 83 1218!83 1218[2 1088 -8 1071!-8 1071[-133 875 -206 752!-206 752[-343 523 -343 447!-343 447[-313 391 -305 337!-305 337[-295 271 -247 271!-247 271[-219 271 -193 301!-193 301
[-165 334 -97 448!-97 448[-40 545 -8 571!-8 571[11 587 17 608!17 608[47 716 238 962!238 962[422 1197 422 1202!422 1202[439 1190 470 1135!470 1135[499 1082 501 1068!501 1068[375 1034 320 946!320 946[292 894 274 865!274 865[242 814 199
 775!199 775[160 740 111 665!111 665[61 588 51 578!51 578[45 572 -35 444!-35 444[-119 310 -156 266!-156 266[-188 229 -241 170!-241 170[-278 117 -278 41!-278 41[-278 -17 -269 -22!-269 -22[-239 -37 -233 -44!-233 -44[-141 -160 -99 -222!-99
 -222[-77 -222 31 -187!31 -187[139 -152 160 -152!160 -152[184 -152 203 -165!203 -165[219 -176 219 -184!219 -184[219 -208 175 -233!175 -233[128 -260 74 -260!74 -260[56 -260 -16 -288!-16 -288[-102 -322 -142 -332!-142 -332[-189 -341 -189
 -371!-189 -371[-189 -624 -113 -661!-113 -661[-94 -671 -61 -680!-61 -680[-37 -693 -37 -743!-37 -743[-37 -762 -71 -785!-71 -785[-105 -808 -105 -813!-105 -813[-105 -828 -86 -938!-86 -938[-68 -1049 -50 -1141!-50 -1141[-43 -1153 -38 -1158
!-38 -1158[-30 -1165 -17 -1165!-17 -1165[-2 -1165 14 -1154!14 -1154[63 -1120 154 -1069!154 -1069[134 -1106 64 -1225!64 -1225[29 -1285 29 -1302!29 -1302[29 -1326 53 -1420!53 -1420[88 -1557 155 -1755!155 -1755[199 -1884 210 -1909!210 -1909
[222 -1933 261 -1994!261 -1994[296 -1985 305 -1971!305 -1971[317 -1955 321 -1898!321 -1898[331 -1668 360.5 -1365"/>
                        <Edge fillStyle1="2" edges="
!360.5 -1365[364 -1336 369 -1286!369 -1286[378 -1183 386 -1017"/>
                        <Edge fillStyle0="1" fillStyle1="2" edges="
!-405 -314[-376 -330 -353 -330!-353 -330[-316 -330 -262 -317!-262 -317[-214 -305 -204 -298!-204 -298[-207 -247 -259 -227!-259 -227[-312 -206 -362 -242!-362 -242[-370 -248 -380 -269!-380 -269[-396 -300 -405 -314"/>
                        <Edge cubics="!386 -1017(386,-1017;384,-996 379,-975 374,-956q386 -1017Q382 -986q374 -956)374,-956;"/>
                        <Edge cubics="!386 -1017(;388,-994 447,-606 489,-368q386 -1017Q388 -994q423 -773Q461 -527q489 -368);"/>
                        <Edge cubics="!489 -368(;495,-332 553,-293 563,-276q489 -368Q493 -347q525 -315Q562 -278q563 -276)563,-276;"/>
                        <Edge cubics="!563 -276(;574,-256 578,-172 585,-125q563 -276Q570 -264q576 -211Q585 -126q585 -125);"/>
                        <Edge cubics="!585 -125(;623,138 643,688 636,777q585 -125Q611 54q627 391Q642 697q636 777);"/>
                        <Edge cubics="!636 777(;630,863 662,948 662,1113q636 777Q633 817q647 915Q662 1026q662 1113);"/>
                        <Edge cubics="!662 1113(;662,1403 640,1174 308,1829q662 1113Q662 1220q653 1255Q645 1288q610 1334Q462 1525q308 1829);"/>
                        <Edge cubics="!308 1829(;260,1923 137,2119 104,2119q308 1829Q265 1913q200 2009Q127 2119q104 2119);"/>
                        <Edge cubics="!104 2119(;-255,2119 -38,2182 -352,1475q104 2119Q-66 2119q-75 2118Q-121 2111q-141 2062Q-195 1829q-352 1475);"/>
                        <Edge cubics="!-352 1475(;-430,1300 -479,966 -572,742q-352 1475Q-390 1389q-456 1127Q-525 856q-572 742);"/>
                        <Edge cubics="!-572 742(;-579,725 -619,645 -623,628q-572 742Q-619 645q-623 628);"/>
                        <Edge cubics="!-623 628(;-641,562 -661,513 -661,395q-623 628Q-647 542q-649 531Q-661 471q-661 395);"/>
                        <Edge cubics="!-661 395(;-661,334 -600,-93 -537,-171q-661 395Q-661 324q-623 118Q-578 -120q-537 -171);"/>
                        <Edge cubics="!-537 -171(;-481,-240 -403,-175 -403,-232q-537 -171Q-508 -207q-449 -206Q-403 -205q-403 -232);"/>
                        <Edge cubics="!-403 -232(;-403,-235 -459,-319 -459,-329q-403 -232Q-459 -319q-459 -329);"/>
                        <Edge cubics="!-459 -329(;-459,-337 -416,-485 -386,-585q-459 -329Q-459 -342q-386 -585);"/>
                        <Edge cubics="!-386 -585(;-370,-637 -414,-522 -274,-901q-386 -585Q-378 -611q-376 -620Q-364 -658q-274 -901);"/>
                        <Edge cubics="!-274 -901(;-208,-1080 -212,-1064 -197,-1113q-274 -901Q-203 -1094q-197 -1113);"/>
                        <Edge cubics="!-197 -1113(;-165,-1214 -149,-1232 -96,-1289q-197 -1113Q-174 -1184q-154 -1217Q-139 -1242q-96 -1289);"/>
                        <Edge cubics="!-96 -1289(;-44,-1345 -35,-1362 -31,-1379q-96 -1289Q-37 -1352q-31 -1379);"/>
                        <Edge cubics="!-31 -1379(;107,-1876 92,-1878 128,-1920q-31 -1379Q-14 -1440q87 -1820Q107 -1895q128 -1920);"/>
                        <Edge cubics="!128 -1920(;175,-1974 125,-2051 175,-2093q128 -1920Q151 -1947q150 -2011Q150 -2072q175 -2093);"/>
                        <Edge cubics="!175 -2093(;188,-2104 192,-2116 218,-2116q175 -2093Q182 -2098q192 -2109Q202 -2116q218 -2116);"/>
                        <Edge cubics="!218 -2116(;238,-2116 231,-2115 245,-2112q218 -2116Q230 -2116q234 -2115Q236 -2114q245 -2112);"/>
                        <Edge cubics="!245 -2112(;245,-2112 334,-2086 337,-2083q245 -2112Q334 -2086q337 -2083);"/>
                        <Edge cubics="!337 -2083(;339,-2081 332,-1945 332,-1906q337 -2083Q332 -1945q332 -1906);"/>
                        <Edge cubics="!332 -1906(;332,-1850 361,-1472 361,-1365q332 -1906Q332 -1884q347 -1655Q361 -1425q361 -1365);"/>
                        <Edge cubics="!374 -956(;351,-965 204,-1004 198,-1005q374 -956Q204 -1004q198 -1005);"/>
                        <Edge cubics="!198 -1005(;198,-1005 192,-1000 192,-1000q198 -1005 192 -1000);"/>
                        <Edge cubics="!192 -1000(;301,-813 428,-740 428,-566q192 -1000Q306 -841q351 -778Q428 -670q428 -566);"/>
                        <Edge cubics="!428 -566(;428,-505 480,-456 480,-288q428 -566Q428 -549q454 -467Q480 -385q480 -288);"/>
                        <Edge cubics="!480 -288(;480,-228 388,-253 364,-253q480 -288Q480 -250q431 -248Q376 -253q364 -253);"/>
                        <Edge cubics="!364 -253(;328,-253 333,-200 310,-170q364 -253Q343 -253q332 -223Q316 -178q310 -170);"/>
                        <Edge cubics="!310 -170(;354,-160 365,-157 385,-157q310 -170Q367 -157q385 -157);"/>
                        <Edge cubics="!385 -157(;483,-157 477,-181 521,-207q385 -157Q446 -157q473 -172Q490 -181q521 -207);"/>
                        <Edge cubics="!521 -207(;533,-194 539,-186 539,-166q521 -207Q531 -196q535 -189Q539 -180q539 -166);"/>
                        <Edge cubics="!539 -166(;539,-146 522,-99 522,-79q539 -166Q539 -156q531 -122Q522 -89q522 -79);"/>
                        <Edge cubics="!522 -79(;522,80 589,556 591,655q522 -79Q522 10q556 311Q590 617q591 655);"/>
                        <Edge cubics="!591 655(;596,842 585,975 605,1104q591 655Q591 660q592 901Q593 1027q605 1104);"/>
                        <Edge cubics="!605 1104(;450,1157 522,1137 496,1205q605 1104Q507 1137q502 1149Q498 1159q496 1205);"/>
                        <Edge cubics="!496 1205(;474,1262 419,1324 419,1336q496 1205Q484 1237q449 1287Q419 1332q419 1336);"/>
                        <Edge cubics="!419 1336(;419,1363 430,1380 451,1380q419 1336Q419 1380q451 1380);"/>
                        <Edge cubics="!451 1380(;471,1380 475,1375 486,1362q451 1380Q465 1380q472 1376Q477 1373q486 1362);"/>
                        <Edge cubics="!486 1362(;493,1368 501,1375 501,1395q486 1362Q501 1375q501 1395);"/>
                        <Edge cubics="!501 1395(;501,1410 344,1741 257,1742q501 1395Q344 1741q257 1742);"/>
                        <Edge cubics="!257 1742(;192,1742 211,1852 102,2015q257 1742Q223 1742q196 1817Q153 1939q102 2015);"/>
                        <Edge cubics="!102 2015(;6,1872 -5,2097 -225,1177q102 2015Q80 1982q41 1953Q7 1928q-15 1887Q-86 1759q-225 1177);"/>
                        <Edge cubics="!-225 1177(;-337,711 -370,912 -370,730q-225 1177Q-287 920q-339 847Q-361 817q-363 811Q-370 791q-370 730);"/>
                        <Edge cubics="!-370 730(;-370,649 -324,655 -321,655q-370 730Q-370 679q-347 662Q-322 655q-321 655);"/>
                        <Edge cubics="!-321 655(;-309,655 -238,787 -238,790q-321 655Q-313 655q-275 721Q-238 786q-238 790);"/>
                        <Edge cubics="!-238 790(;-238,800 -241,864 -135,1002q-238 790Q-238 868q-135 1002);"/>
                        <Edge cubics="!-135 1002(;-134,1003 7,1289 27,1329q-135 1002 27 1329);"/>
                        <Edge cubics="!27 1329(;55,1386 220,1697 221,1704q27 1329Q55 1386q221 1704);"/>
                        <Edge cubics="!221 1704(;266,1667 246,1615 284,1508q221 1704Q246 1683q255 1632Q270 1548q284 1508);"/>
                        <Edge cubics="!284 1508(;294,1480 359,1420 369,1396q284 1508Q289 1493q327 1451Q364 1407q369 1396);"/>
                        <Edge cubics="!369 1396(;369,1396 372,1378 372,1378q369 1396 372 1378);"/>
                        <Edge cubics="!372 1378(;307,1417 285,1486 242,1486q372 1378Q342 1396q299 1447Q265 1486q242 1486);"/>
                        <Edge cubics="!242 1486(;189,1486 166,1382 153,1341q242 1486Q208 1486q183 1429Q177 1417q153 1341);"/>
                        <Edge cubics="!153 1341(;143,1309 29,1136 -8,1071q153 1341Q147 1322q83 1218Q2 1088q-8 1071);"/>
                        <Edge cubics="!-8 1071(;-90,929 -343,569 -343,447q-8 1071Q-133 875q-206 752Q-343 523q-343 447);"/>
                        <Edge cubics="!-343 447(;-343,446 -313,391 -305,337q-343 447Q-313 391q-305 337);"/>
                        <Edge cubics="!-305 337(;-301,310 -289,271 -247,271q-305 337Q-295 271q-247 271);"/>
                        <Edge cubics="!-247 271(;-211,271 -190,291 -97,448q-247 271Q-219 271q-193 301Q-165 334q-97 448);"/>
                        <Edge cubics="!-97 448(;4,620 2,551 17,608q-97 448Q-40 545q-8 571Q11 587q17 608);"/>
                        <Edge cubics="!17 608(;67,791 422,1170 422,1202q17 608Q47 716q238 962Q422 1197q422 1202);"/>
                        <Edge cubics="!422 1202(;446,1184 499,1085 501,1068q422 1202Q439 1190q470 1135Q499 1082q501 1068);"/>
                        <Edge cubics="!501 1068(;284,1010 337,899 199,775q501 1068Q375 1034q320 946Q292 894q274 865Q242 814q199 775);"/>
                        <Edge cubics="!199 775(;131,714 82,607 51,578q199 775Q160 740q111 665Q61 588q51 578);"/>
                        <Edge cubics="!51 578(;33,561 -91,342 -156,266q51 578Q45 572q-35 444Q-119 310q-156 266);"/>
                        <Edge cubics="!-156 266(;-220,191 -278,159 -278,41q-156 266Q-188 229q-241 170Q-278 117q-278 41);"/>
                        <Edge cubics="!-278 41(;-278,-58 -268,0 -233,-44q-278 41Q-278 -17q-269 -22Q-239 -37q-233 -44);"/>
                        <Edge cubics="!-233 -44(;-141,-160 -99,-222 -99,-222q-233 -44Q-141 -160q-99 -222);"/>
                        <Edge cubics="!-99 -222(;-56,-222 118,-152 160,-152q-99 -222Q-77 -222q31 -187Q139 -152q160 -152);"/>
                        <Edge cubics="!160 -152(;196,-152 219,-176 219,-184q160 -152Q184 -152q203 -165Q219 -176q219 -184);"/>
                        <Edge cubics="!219 -184(;219,-213 150,-260 74,-260q219 -184Q219 -208q175 -233Q128 -260q74 -260);"/>
                        <Edge cubics="!74 -260(;40,-260 -59,-311 -142,-332q74 -260Q56 -260q-16 -288Q-102 -322q-142 -332);"/>
                        <Edge cubics="!-142 -332(-142,-332;-152,-334 -189,-344 -189,-371q-142 -332Q-189 -341q-189 -371);"/>
                        <Edge cubics="!-189 -371(;-189,-807 -37,-585 -37,-743q-189 -371Q-189 -624q-113 -661Q-94 -671q-61 -680Q-37 -693q-37 -743);"/>
                        <Edge cubics="!-37 -743(;-37,-777 -105,-799 -105,-813q-37 -743Q-37 -762q-71 -785Q-105 -808q-105 -813);"/>
                        <Edge cubics="!-105 -813(;-105,-833 -74,-1018 -50,-1141q-105 -813Q-105 -828q-86 -938Q-68 -1049q-50 -1141);"/>
                        <Edge cubics="!-50 -1141(;-43,-1154 -37,-1165 -17,-1165q-50 -1141Q-43 -1153q-38 -1158Q-30 -1165q-17 -1165);"/>
                        <Edge cubics="!-17 -1165(;14,-1165 -23,-1168 154,-1069q-17 -1165Q-2 -1165q14 -1154Q63 -1120q154 -1069);"/>
                        <Edge cubics="!154 -1069(;81,-1204 29,-1273 29,-1302q154 -1069Q134 -1106q64 -1225Q29 -1285q29 -1302);"/>
                        <Edge cubics="!29 -1302(;29,-1319 51,-1449 155,-1755q29 -1302Q29 -1326q53 -1420Q88 -1557q155 -1755);"/>
                        <Edge cubics="!155 -1755(;219,-1945 203,-1896 261,-1994q155 -1755Q199 -1884q210 -1909Q222 -1933q261 -1994);"/>
                        <Edge cubics="!261 -1994(261,-1994;349,-1971 300,-1972 361,-1365q261 -1994Q296 -1985q305 -1971Q317 -1955q321 -1898Q331 -1668q361 -1365);"/>
                        <Edge cubics="!361 -1365(;361,-1344 373,-1292 386,-1017q361 -1365Q364 -1336q369 -1286Q378 -1183q386 -1017);"/>
                        <Edge cubics="!-405 -314(;-387,-324 -373,-330 -353,-330q-405 -314Q-376 -330q-353 -330);"/>
                        <Edge cubics="!-353 -330(;-298,-330 -214,-305 -204,-298q-353 -330Q-316 -330q-262 -317Q-214 -305q-204 -298);"/>
                        <Edge cubics="!-204 -298(;-208,-233 -294,-192 -362,-242q-204 -298Q-207 -247q-259 -227Q-312 -206q-362 -242);"/>
                        <Edge cubics="!-362 -242(;-376,-252 -383,-280 -405,-314q-362 -242Q-370 -248q-380 -269Q-396 -300q-405 -314);"/>
                      </edges>
                    </DOMShape>
                  </members>
                </DOMGroup>
              </elements>
            </DOMFrame>
          </frames>
        </DOMLayer>
      </layers>
    </DOMTimeline>
  </timeline>
</DOMSymbolItem>